bandcamp_async_api/__init__.py
bandcamp_async_api/client.py
bandcamp_async_api/models.py
bandcamp_async_api/parsers.py
bandcamp_async_api-0.0.7.dist-info/WHEEL
bandcamp_async_api-0.0.7.dist-info/WHEEL.json
bandcamp_async_api-0.0.7.dist-info/METADATA
bandcamp_async_api-0.0.7.dist-info/METADATA.json
bandcamp_async_api-0.0.7.dist-info/RECORD
