Metadata-Version: 2.3
Name: bandcamp-async-api
Version: 0.0.7
Summary: Bandcamp Async API
Keywords: bandcamp,api,async
Author: Alexey ALERT Rubashёff
Author-email: Alexey ALERT Rubashёff <alexey.rubasheff@gmail.com>
Classifier: Topic :: Software Development :: Libraries :: Python Modules
Requires-Dist: aiohttp
Requires-Python: >=3.12
Project-URL: homepage, https://github.com/ALERTua/bandcamp_async_api
Project-URL: repository, https://github.com/ALERTua/bandcamp_async_api
Project-URL: documentation, https://github.com/ALERTua/bandcamp_async_api
Project-URL: Bug Tracker, https://github.com/ALERTua/bandcamp_async_api/issues
